mopidy_moparty/__init__.py
mopidy_moparty/ext.conf
mopidy_moparty/static/.DS_Store
mopidy_moparty/static/index.html
mopidy_moparty/static/moparty.min.js
mopidy_moparty/static/img/.DS_Store
mopidy_moparty/static/img/arrow-right.svg
mopidy_moparty/static/img/arrow-up.svg
mopidy_moparty/static/img/check.svg
mopidy_moparty/static/img/pause.svg
mopidy_moparty/static/img/play.svg
mopidy_moparty/static/img/plus.svg
mopidy_moparty/static/img/search.svg
mopidy_moparty/static/img/step-forward.svg
mopidy_moparty/static/img/stop.svg
Mopidy_Moparty-0.3.2.dist-info/LICENSE
Mopidy_Moparty-0.3.2.dist-info/METADATA
Mopidy_Moparty-0.3.2.dist-info/WHEEL
Mopidy_Moparty-0.3.2.dist-info/entry_points.txt
Mopidy_Moparty-0.3.2.dist-info/top_level.txt
Mopidy_Moparty-0.3.2.dist-info/RECORD
